{"tempo": 129.19921875, "lanes": 4, "events": [{"id": 1, "time": 0.31, "type": "normal", "lane": 2}, {"id": 2, "time": 1.1863, "type": "normal", "lane": 1}, {"id": 3, "time": 1.6463, "type": "normal", "lane": 0}, {"id": 4, "time": 2.0583, "type": "normal", "lane": 0}, {"id": 5, "time": 2.6544, "type": "normal", "lane": 1}, {"id": 6, "time": 3.1072, "type": "normal", "lane": 0}, {"id": 7, "time": 3.648, "type": "normal", "lane": 1}, {"id": 8, "time": 4.108, "type": "normal", "lane": 0}, {"id": 9, "time": 4.5144, "type": "normal", "lane": 1}, {"id": 10, "time": 4.9944, "type": "normal", "lane": 0}, {"id": 11, "time": 5.2802, "type": "normal", "lane": 1}, {"id": 12, "time": 5.8663, "type": "normal", "lane": 0}, {"id": 13, "time": 6.1241, "type": "normal", "lane": 1}, {"id": 14, "time": 6.4144, "type": "normal", "lane": 0}, {"id": 15, "time": 6.8744, "type": "normal", "lane": 1}, {"id": 16, "time": 7.3344, "type": "normal", "lane": 0}, {"id": 17, "time": 7.7083, "type": "normal", "lane": 1}, {"id": 18, "time": 8.0902, "type": "normal", "lane": 0}, {"id": 19, "time": 8.3761, "type": "normal", "lane": 1}, {"id": 20, "time": 8.6663, "type": "normal", "lane": 0}, {"id": 21, "time": 9.0202, "type": "normal", "lane": 1}, {"id": 22, "time": 9.1944, "type": "strong", "lane": 2}, {"id": 23, "time": 9.6163, "type": "normal", "lane": 1}, {"id": 24, "time": 9.9702, "type": "normal", "lane": 0}, {"id": 25, "time": 10.208, "type": "normal", "lane": 1}, {"id": 26, "time": 10.5563, "type": "normal", "lane": 0}, {"id": 27, "time": 10.8522, "type": "normal", "lane": 1}, {"id": 28, "time": 11.0844, "type": "strong", "lane": 2}, {"id": 29, "time": 11.5522, "type": "strong", "lane": 1}, {"id": 30, "time": 11.7822, "type": "normal", "lane": 0}, {"id": 31, "time": 12.2522, "type": "normal", "lane": 1}, {"id": 32, "time": 12.7222, "type": "normal", "lane": 0}, {"id": 33, "time": 13.1922, "type": "normal", "lane": 1}, {"id": 34, "time": 13.6041, "type": "normal", "lane": 0}, {"id": 35, "time": 13.8944, "type": "strong", "lane": 1}, {"id": 36, "time": 14.2483, "type": "normal", "lane": 1}, {"id": 37, "time": 14.6022, "type": "normal", "lane": 0}, {"id": 38, "time": 14.8322, "type": "strong", "lane": 2}, {"id": 39, "time": 15.2972, "type": "normal", "lane": 1}, {"id": 40, "time": 15.6483, "type": "normal", "lane": 0}, {"id": 41, "time": 15.9541, "type": "normal", "lane": 1}, {"id": 42, "time": 16.2444, "type": "strong", "lane": 2}, {"id": 43, "time": 16.6563, "type": "normal", "lane": 0}, {"id": 44, "time": 17.0002, "type": "normal", "lane": 0}, {"id": 45, "time": 17.3541, "type": "normal", "lane": 1}, {"id": 46, "time": 17.708, "type": "normal", "lane": 1}, {"id": 47, "time": 18.5163, "type": "normal", "lane": 0}, {"id": 48, "time": 18.8802, "type": "normal", "lane": 0}, {"id": 49, "time": 19.2822, "type": "normal", "lane": 1}, {"id": 50, "time": 19.6461, "type": "normal", "lane": 0}, {"id": 51, "time": 19.9363, "type": "normal", "lane": 1}, {"id": 52, "time": 20.3963, "type": "normal", "lane": 3}, {"id": 53, "time": 20.6341, "type": "normal", "lane": 3}, {"id": 54, "time": 21.0461, "type": "normal", "lane": 0}, {"id": 55, "time": 21.2202, "type": "normal", "lane": 1}, {"id": 56, "time": 21.458, "type": "normal", "lane": 0}, {"id": 57, "time": 22.1502, "type": "normal", "lane": 1}, {"id": 58, "time": 22.3244, "type": "normal", "lane": 1}, {"id": 59, "time": 22.9741, "type": "normal", "lane": 0}, {"id": 60, "time": 23.2644, "type": "normal", "lane": 1}, {"id": 61, "time": 23.5122, "type": "normal", "lane": 0}, {"id": 62, "time": 23.8561, "type": "normal", "lane": 1}, {"id": 63, "time": 24.1463, "type": "normal", "lane": 0}, {"id": 64, "time": 24.4902, "type": "normal", "lane": 0}, {"id": 65, "time": 24.738, "type": "normal", "lane": 1}, {"id": 66, "time": 25.0283, "type": "normal", "lane": 0}, {"id": 67, "time": 25.2661, "type": "normal", "lane": 1}, {"id": 68, "time": 25.7841, "type": "normal", "lane": 0}, {"id": 69, "time": 26.1961, "type": "normal", "lane": 1}, {"id": 70, "time": 26.4863, "type": "normal", "lane": 0}, {"id": 71, "time": 26.7822, "type": "normal", "lane": 1}, {"id": 72, "time": 27.1361, "type": "normal", "lane": 0}, {"id": 73, "time": 27.3683, "type": "normal", "lane": 2}, {"id": 74, "time": 27.7122, "type": "normal", "lane": 1}, {"id": 75, "time": 27.9444, "type": "normal", "lane": 0}, {"id": 76, "time": 28.3563, "type": "normal", "lane": 1}, {"id": 77, "time": 28.6522, "type": "normal", "lane": 2}, {"id": 78, "time": 29.1222, "type": "normal", "lane": 1}, {"id": 79, "time": 29.3544, "type": "strong", "lane": 1}, {"id": 80, "time": 29.5922, "type": "normal", "lane": 0}, {"id": 81, "time": 30.0622, "type": "normal", "lane": 1}, {"id": 82, "time": 30.2363, "type": "normal", "lane": 0}, {"id": 83, "time": 30.5322, "type": "normal", "lane": 3}, {"id": 84, "time": 30.828, "type": "normal", "lane": 1}, {"id": 85, "time": 31.298, "type": "normal", "lane": 0}, {"id": 86, "time": 31.4722, "type": "normal", "lane": 1}, {"id": 87, "time": 31.8261, "type": "normal", "lane": 0}, {"id": 88, "time": 32.1744, "type": "strong", "lane": 2}, {"id": 89, "time": 32.6444, "type": "strong", "lane": 1}, {"id": 90, "time": 33.1072, "type": "strong", "lane": 2}, {"id": 91, "time": 33.5744, "type": "strong", "lane": 1}, {"id": 92, "time": 33.9283, "type": "normal", "lane": 1}, {"id": 93, "time": 34.2241, "type": "normal", "lane": 0}, {"id": 94, "time": 34.5144, "type": "strong", "lane": 2}, {"id": 95, "time": 34.9844, "type": "strong", "lane": 1}, {"id": 96, "time": 35.4544, "type": "strong", "lane": 2}, {"id": 97, "time": 35.6822, "type": "normal", "lane": 0}, {"id": 98, "time": 36.1522, "type": "normal", "lane": 2}, {"id": 99, "time": 36.448, "type": "normal", "lane": 1}, {"id": 100, "time": 36.6802, "type": "normal", "lane": 0}, {"id": 101, "time": 36.8572, "type": "strong", "lane": 1}, {"id": 102, "time": 37.2663, "type": "normal", "lane": 1}, {"id": 103, "time": 37.5041, "type": "normal", "lane": 0}, {"id": 104, "time": 38.1102, "type": "normal", "lane": 3}, {"id": 105, "time": 38.2844, "type": "strong", "lane": 1}, {"id": 106, "time": 38.4541, "type": "normal", "lane": 1}, {"id": 107, "time": 38.6863, "type": "normal", "lane": 1}, {"id": 108, "time": 38.9141, "type": "normal", "lane": 0}, {"id": 109, "time": 39.268, "type": "normal", "lane": 1}, {"id": 110, "time": 39.7861, "type": "normal", "lane": 0}, {"id": 111, "time": 40.1344, "type": "normal", "lane": 1}, {"id": 112, "time": 40.3722, "type": "normal", "lane": 0}, {"id": 113, "time": 40.7261, "type": "normal", "lane": 1}, {"id": 114, "time": 40.9002, "type": "normal", "lane": 0}, {"id": 115, "time": 41.0744, "type": "strong", "lane": 1}, {"id": 116, "time": 41.3702, "type": "normal", "lane": 0}, {"id": 117, "time": 41.5472, "type": "strong", "lane": 1}, {"id": 118, "time": 41.9563, "type": "normal", "lane": 1}, {"id": 119, "time": 42.3683, "type": "normal", "lane": 1}, {"id": 120, "time": 42.7702, "type": "normal", "lane": 0}, {"id": 121, "time": 42.9472, "type": "strong", "lane": 1}, {"id": 122, "time": 43.2402, "type": "normal", "lane": 1}, {"id": 123, "time": 43.5941, "type": "normal", "lane": 0}, {"id": 124, "time": 43.8872, "type": "strong", "lane": 2}, {"id": 125, "time": 44.3572, "type": "strong", "lane": 1}, {"id": 126, "time": 44.6502, "type": "normal", "lane": 2}, {"id": 127, "time": 45.1202, "type": "normal", "lane": 1}, {"id": 128, "time": 45.4741, "type": "normal", "lane": 0}, {"id": 129, "time": 45.7672, "type": "strong", "lane": 1}, {"id": 130, "time": 46.1183, "type": "normal", "lane": 0}, {"id": 131, "time": 46.8741, "type": "normal", "lane": 1}, {"id": 132, "time": 47.1672, "type": "strong", "lane": 2}, {"id": 133, "time": 47.5183, "type": "normal", "lane": 0}, {"id": 134, "time": 47.9302, "type": "normal", "lane": 1}, {"id": 135, "time": 48.1072, "type": "strong", "lane": 1}, {"id": 136, "time": 48.4583, "type": "normal", "lane": 1}, {"id": 137, "time": 48.7541, "type": "normal", "lane": 0}, {"id": 138, "time": 48.9863, "type": "normal", "lane": 0}, {"id": 139, "time": 49.3402, "type": "normal", "lane": 1}, {"id": 140, "time": 49.8102, "type": "normal", "lane": 0}, {"id": 141, "time": 50.2222, "type": "normal", "lane": 1}, {"id": 142, "time": 50.4533, "type": "strong", "lane": 2}, {"id": 143, "time": 50.6241, "type": "normal", "lane": 1}, {"id": 144, "time": 50.9144, "type": "strong", "lane": 2}, {"id": 145, "time": 51.2683, "type": "normal", "lane": 0}, {"id": 146, "time": 51.6222, "type": "normal", "lane": 1}, {"id": 147, "time": 51.8572, "type": "strong", "lane": 1}, {"id": 148, "time": 52.1502, "type": "normal", "lane": 0}, {"id": 149, "time": 52.4461, "type": "normal", "lane": 1}, {"id": 150, "time": 52.6783, "type": "normal", "lane": 0}, {"id": 151, "time": 52.9741, "type": "normal", "lane": 0}, {"id": 152, "time": 53.5602, "type": "normal", "lane": 1}, {"id": 153, "time": 53.7344, "type": "strong", "lane": 1}, {"id": 154, "time": 54.2044, "type": "strong", "lane": 2}, {"id": 155, "time": 54.4902, "type": "normal", "lane": 0}, {"id": 156, "time": 54.6644, "type": "strong", "lane": 2}, {"id": 157, "time": 55.0183, "type": "normal", "lane": 1}, {"id": 158, "time": 55.4302, "type": "normal", "lane": 1}, {"id": 159, "time": 55.7841, "type": "normal", "lane": 0}, {"id": 160, "time": 55.9583, "type": "normal", "lane": 1}, {"id": 161, "time": 56.3122, "type": "normal", "lane": 0}, {"id": 162, "time": 56.5444, "type": "strong", "lane": 2}, {"id": 163, "time": 56.8983, "type": "normal", "lane": 0}, {"id": 164, "time": 57.3102, "type": "normal", "lane": 1}, {"id": 165, "time": 57.4844, "type": "strong", "lane": 1}, {"id": 166, "time": 57.7802, "type": "normal", "lane": 0}, {"id": 167, "time": 57.9622, "type": "strong", "lane": 1}, {"id": 168, "time": 58.5561, "type": "normal", "lane": 1}, {"id": 169, "time": 59.2583, "type": "normal", "lane": 0}, {"id": 170, "time": 59.418, "type": "normal", "lane": 1}, {"id": 171, "time": 59.8272, "type": "strong", "lane": 1}, {"id": 172, "time": 60.2363, "type": "normal", "lane": 1}, {"id": 173, "time": 60.5322, "type": "normal", "lane": 3}, {"id": 174, "time": 60.7644, "type": "normal", "lane": 0}, {"id": 175, "time": 61.1183, "type": "normal", "lane": 0}, {"id": 176, "time": 61.4141, "type": "normal", "lane": 1}, {"id": 177, "time": 61.768, "type": "normal", "lane": 0}, {"id": 178, "time": 62.1163, "type": "normal", "lane": 1}, {"id": 179, "time": 62.5863, "type": "normal", "lane": 0}, {"id": 180, "time": 62.8722, "type": "normal", "lane": 1}, {"id": 181, "time": 63.2941, "type": "normal", "lane": 0}, {"id": 182, "time": 63.6961, "type": "normal", "lane": 1}, {"id": 183, "time": 63.9863, "type": "normal", "lane": 0}, {"id": 184, "time": 64.3983, "type": "normal", "lane": 1}, {"id": 185, "time": 64.578, "type": "normal", "lane": 1}, {"id": 186, "time": 64.9263, "type": "normal", "lane": 0}, {"id": 187, "time": 65.2222, "type": "normal", "lane": 2}, {"id": 188, "time": 65.6341, "type": "normal", "lane": 0}, {"id": 189, "time": 65.9272, "type": "strong", "lane": 1}, {"id": 190, "time": 66.3363, "type": "normal", "lane": 1}, {"id": 191, "time": 66.5741, "type": "normal", "lane": 1}, {"id": 192, "time": 66.8063, "type": "normal", "lane": 0}, {"id": 193, "time": 67.1022, "type": "normal", "lane": 3}, {"id": 194, "time": 67.388, "type": "normal", "lane": 0}, {"id": 195, "time": 67.6202, "type": "normal", "lane": 1}, {"id": 196, "time": 68.1483, "type": "normal", "lane": 0}, {"id": 197, "time": 68.5022, "type": "normal", "lane": 2}, {"id": 198, "time": 68.7372, "type": "strong", "lane": 2}, {"id": 199, "time": 69.0883, "type": "normal", "lane": 1}, {"id": 200, "time": 69.3841, "type": "normal", "lane": 0}, {"id": 201, "time": 69.6733, "type": "strong", "lane": 1}, {"id": 202, "time": 70.1422, "type": "strong", "lane": 2}, {"id": 203, "time": 70.6133, "type": "strong", "lane": 1}, {"id": 204, "time": 70.9583, "type": "normal", "lane": 1}, {"id": 205, "time": 71.1961, "type": "normal", "lane": 1}, {"id": 206, "time": 71.3702, "type": "normal", "lane": 0}, {"id": 207, "time": 71.7241, "type": "normal", "lane": 1}, {"id": 208, "time": 72.078, "type": "normal", "lane": 0}, {"id": 209, "time": 72.4872, "type": "strong", "lane": 1}, {"id": 210, "time": 72.9572, "type": "strong", "lane": 2}, {"id": 211, "time": 73.3663, "type": "normal", "lane": 0}, {"id": 212, "time": 73.7202, "type": "normal", "lane": 1}, {"id": 213, "time": 74.1322, "type": "normal", "lane": 3}, {"id": 214, "time": 74.4761, "type": "normal", "lane": 0}, {"id": 215, "time": 74.7663, "type": "normal", "lane": 1}, {"id": 216, "time": 75.2463, "type": "normal", "lane": 1}, {"id": 217, "time": 75.6002, "type": "normal", "lane": 0}, {"id": 218, "time": 75.9641, "type": "normal", "lane": 1}, {"id": 219, "time": 76.2472, "type": "strong", "lane": 1}, {"id": 220, "time": 76.5883, "type": "normal", "lane": 0}, {"id": 221, "time": 76.8841, "type": "normal", "lane": 0}, {"id": 222, "time": 77.1722, "type": "strong", "lane": 2}, {"id": 223, "time": 77.6372, "type": "strong", "lane": 1}, {"id": 224, "time": 77.9302, "type": "normal", "lane": 1}, {"id": 225, "time": 78.1072, "type": "strong", "lane": 1}, {"id": 226, "time": 78.2841, "type": "normal", "lane": 0}, {"id": 227, "time": 78.9383, "type": "normal", "lane": 1}, {"id": 228, "time": 79.4763, "type": "normal", "lane": 2}, {"id": 229, "time": 79.7722, "type": "normal", "lane": 0}, {"id": 230, "time": 80.1061, "type": "normal", "lane": 1}, {"id": 231, "time": 80.4544, "type": "strong", "lane": 1}, {"id": 232, "time": 80.8663, "type": "normal", "lane": 0}, {"id": 233, "time": 81.2883, "type": "normal", "lane": 1}, {"id": 234, "time": 81.5161, "type": "normal", "lane": 0}, {"id": 235, "time": 81.928, "type": "normal", "lane": 1}, {"id": 236, "time": 82.2183, "type": "normal", "lane": 3}, {"id": 237, "time": 82.5722, "type": "normal", "lane": 0}, {"id": 238, "time": 83.0422, "type": "normal", "lane": 1}, {"id": 239, "time": 83.4441, "type": "normal", "lane": 0}, {"id": 240, "time": 83.7372, "type": "strong", "lane": 2}, {"id": 241, "time": 84.2044, "type": "strong", "lane": 1}, {"id": 242, "time": 84.6163, "type": "normal", "lane": 1}, {"id": 243, "time": 84.9702, "type": "normal", "lane": 1}, {"id": 244, "time": 85.2561, "type": "normal", "lane": 0}, {"id": 245, "time": 85.6044, "type": "strong", "lane": 1}, {"id": 246, "time": 86.0063, "type": "normal", "lane": 1}, {"id": 247, "time": 86.5344, "type": "normal", "lane": 0}, {"id": 248, "time": 86.8502, "type": "normal", "lane": 1}, {"id": 249, "time": 87.0244, "type": "strong", "lane": 1}, {"id": 250, "time": 87.6161, "type": "normal", "lane": 0}, {"id": 251, "time": 87.9644, "type": "strong", "lane": 1}, {"id": 252, "time": 88.4344, "type": "normal", "lane": 0}, {"id": 253, "time": 88.8944, "type": "normal", "lane": 1}, {"id": 254, "time": 89.0261, "type": "normal", "lane": 1}, {"id": 255, "time": 89.3722, "type": "strong", "lane": 1}, {"id": 256, "time": 89.8322, "type": "strong", "lane": 2}, {"id": 257, "time": 90.1783, "type": "normal", "lane": 0}, {"id": 258, "time": 90.4741, "type": "normal", "lane": 1}, {"id": 259, "time": 90.9441, "type": "normal", "lane": 0}, {"id": 260, "time": 91.2372, "type": "strong", "lane": 2}, {"id": 261, "time": 91.5883, "type": "normal", "lane": 0}, {"id": 262, "time": 91.8841, "type": "normal", "lane": 1}, {"id": 263, "time": 92.1744, "type": "strong", "lane": 1}, {"id": 264, "time": 92.5763, "type": "normal", "lane": 1}, {"id": 265, "time": 92.9302, "type": "normal", "lane": 0}, {"id": 266, "time": 93.4002, "type": "normal", "lane": 1}, {"id": 267, "time": 93.5772, "type": "strong", "lane": 1}, {"id": 268, "time": 93.8702, "type": "normal", "lane": 0}, {"id": 269, "time": 94.0472, "type": "strong", "lane": 1}, {"id": 270, "time": 94.3983, "type": "normal", "lane": 0}, {"id": 271, "time": 94.8102, "type": "normal", "lane": 1}, {"id": 272, "time": 94.9844, "type": "strong", "lane": 2}, {"id": 273, "time": 95.3963, "type": "normal", "lane": 2}, {"id": 274, "time": 95.6822, "type": "normal", "lane": 0}, {"id": 275, "time": 95.9172, "type": "strong", "lane": 1}, {"id": 276, "time": 96.2683, "type": "normal", "lane": 1}, {"id": 277, "time": 96.6802, "type": "normal", "lane": 1}, {"id": 278, "time": 97.0341, "type": "normal", "lane": 0}, {"id": 279, "time": 97.388, "type": "normal", "lane": 0}, {"id": 280, "time": 97.6202, "type": "normal", "lane": 1}, {"id": 281, "time": 97.858, "type": "normal", "lane": 0}, {"id": 282, "time": 98.0322, "type": "normal", "lane": 3}, {"id": 283, "time": 98.5022, "type": "normal", "lane": 2}, {"id": 284, "time": 98.9722, "type": "normal", "lane": 3}, {"id": 285, "time": 99.3261, "type": "normal", "lane": 1}, {"id": 286, "time": 99.6733, "type": "strong", "lane": 2}, {"id": 287, "time": 100.0183, "type": "normal", "lane": 1}, {"id": 288, "time": 100.3141, "type": "normal", "lane": 0}, {"id": 289, "time": 100.6044, "type": "strong", "lane": 1}, {"id": 290, "time": 100.9583, "type": "normal", "lane": 0}, {"id": 291, "time": 101.1961, "type": "normal", "lane": 1}, {"id": 292, "time": 101.4863, "type": "normal", "lane": 0}, {"id": 293, "time": 101.8402, "type": "normal", "lane": 1}, {"id": 294, "time": 102.1361, "type": "normal", "lane": 0}, {"id": 295, "time": 102.4872, "type": "strong", "lane": 1}, {"id": 296, "time": 102.8383, "type": "normal", "lane": 1}, {"id": 297, "time": 103.0761, "type": "normal", "lane": 0}, {"id": 298, "time": 103.3663, "type": "normal", "lane": 1}, {"id": 299, "time": 103.7302, "type": "normal", "lane": 0}, {"id": 300, "time": 104.0161, "type": "normal", "lane": 1}, {"id": 301, "time": 104.3063, "type": "normal", "lane": 1}, {"id": 302, "time": 104.5341, "type": "normal", "lane": 0}, {"id": 303, "time": 105.1302, "type": "normal", "lane": 0}, {"id": 304, "time": 105.4161, "type": "normal", "lane": 1}, {"id": 305, "time": 105.6483, "type": "normal", "lane": 1}, {"id": 306, "time": 105.9441, "type": "normal", "lane": 0}, {"id": 307, "time": 106.2372, "type": "strong", "lane": 1}, {"id": 308, "time": 106.5302, "type": "normal", "lane": 1}, {"id": 309, "time": 107.0002, "type": "normal", "lane": 0}, {"id": 310, "time": 107.1772, "type": "strong", "lane": 2}, {"id": 311, "time": 107.6444, "type": "strong", "lane": 1}, {"id": 312, "time": 107.9883, "type": "normal", "lane": 1}, {"id": 313, "time": 108.5163, "type": "normal", "lane": 3}, {"id": 314, "time": 108.8702, "type": "normal", "lane": 0}, {"id": 315, "time": 109.2241, "type": "normal", "lane": 1}, {"id": 316, "time": 109.3983, "type": "normal", "lane": 0}, {"id": 317, "time": 109.7522, "type": "normal", "lane": 0}, {"id": 318, "time": 109.9263, "type": "normal", "lane": 1}, {"id": 319, "time": 110.2802, "type": "normal", "lane": 2}, {"id": 320, "time": 110.508, "type": "normal", "lane": 0}, {"id": 321, "time": 110.7402, "type": "normal", "lane": 1}, {"id": 322, "time": 111.0941, "type": "normal", "lane": 0}, {"id": 323, "time": 111.3872, "type": "strong", "lane": 1}, {"id": 324, "time": 111.7383, "type": "normal", "lane": 1}, {"id": 325, "time": 111.9761, "type": "normal", "lane": 0}, {"id": 326, "time": 112.3244, "type": "strong", "lane": 2}, {"id": 327, "time": 112.6783, "type": "normal", "lane": 1}, {"id": 328, "time": 113.1483, "type": "normal", "lane": 0}, {"id": 329, "time": 113.5602, "type": "normal", "lane": 1}, {"id": 330, "time": 113.7322, "type": "strong", "lane": 2}, {"id": 331, "time": 114.1363, "type": "normal", "lane": 1}, {"id": 332, "time": 114.4322, "type": "normal", "lane": 0}, {"id": 333, "time": 114.6063, "type": "normal", "lane": 0}, {"id": 334, "time": 115.0183, "type": "normal", "lane": 1}, {"id": 335, "time": 115.4302, "type": "normal", "lane": 1}, {"id": 336, "time": 115.9002, "type": "normal", "lane": 0}, {"id": 337, "time": 116.2541, "type": "normal", "lane": 0}, {"id": 338, "time": 116.4283, "type": "normal", "lane": 1}, {"id": 339, "time": 116.6661, "type": "normal", "lane": 0}, {"id": 340, "time": 116.8983, "type": "normal", "lane": 1}, {"id": 341, "time": 117.2522, "type": "normal", "lane": 1}, {"id": 342, "time": 117.4263, "type": "normal", "lane": 0}, {"id": 343, "time": 117.6541, "type": "normal", "lane": 1}, {"id": 344, "time": 117.8283, "type": "normal", "lane": 0}, {"id": 345, "time": 118.008, "type": "normal", "lane": 0}, {"id": 346, "time": 118.2402, "type": "normal", "lane": 1}, {"id": 347, "time": 118.4144, "type": "strong", "lane": 1}, {"id": 348, "time": 118.7683, "type": "normal", "lane": 1}, {"id": 349, "time": 119.0641, "type": "normal", "lane": 0}, {"id": 350, "time": 119.2383, "type": "normal", "lane": 0}, {"id": 351, "time": 119.6502, "type": "normal", "lane": 1}, {"id": 352, "time": 120.0041, "type": "normal", "lane": 0}, {"id": 353, "time": 120.2944, "type": "strong", "lane": 1}, {"id": 354, "time": 120.6483, "type": "normal", "lane": 1}, {"id": 355, "time": 121.0602, "type": "normal", "lane": 1}, {"id": 356, "time": 121.2322, "type": "strong", "lane": 2}, {"id": 357, "time": 121.6363, "type": "normal", "lane": 0}, {"id": 358, "time": 121.9422, "type": "normal", "lane": 1}, {"id": 359, "time": 122.1163, "type": "normal", "lane": 0}, {"id": 360, "time": 122.4602, "type": "normal", "lane": 1}, {"id": 361, "time": 122.9302, "type": "normal", "lane": 0}, {"id": 362, "time": 123.4002, "type": "normal", "lane": 1}, {"id": 363, "time": 123.638, "type": "normal", "lane": 0}, {"id": 364, "time": 123.8702, "type": "normal", "lane": 1}, {"id": 365, "time": 124.1661, "type": "normal", "lane": 0}, {"id": 366, "time": 124.3983, "type": "normal", "lane": 1}, {"id": 367, "time": 124.6361, "type": "normal", "lane": 0}, {"id": 368, "time": 124.9263, "type": "normal", "lane": 1}, {"id": 369, "time": 125.2702, "type": "normal", "lane": 0}, {"id": 370, "time": 125.508, "type": "normal", "lane": 0}, {"id": 371, "time": 125.7402, "type": "normal", "lane": 1}, {"id": 372, "time": 126.0361, "type": "normal", "lane": 0}, {"id": 373, "time": 126.448, "type": "normal", "lane": 1}, {"id": 374, "time": 126.7963, "type": "normal", "lane": 1}, {"id": 375, "time": 127.1502, "type": "normal", "lane": 0}, {"id": 376, "time": 127.5041, "type": "normal", "lane": 1}, {"id": 377, "time": 127.7933, "type": "strong", "lane": 1}, {"id": 378, "time": 128.1383, "type": "normal", "lane": 0}, {"id": 379, "time": 128.5602, "type": "normal", "lane": 1}, {"id": 380, "time": 128.7344, "type": "strong", "lane": 2}, {"id": 381, "time": 129.1944, "type": "normal", "lane": 0}, {"id": 382, "time": 129.4902, "type": "normal", "lane": 0}, {"id": 383, "time": 129.7861, "type": "normal", "lane": 1}, {"id": 384, "time": 130.1372, "type": "normal", "lane": 1}, {"id": 385, "time": 130.3722, "type": "normal", "lane": 0}, {"id": 386, "time": 130.5463, "type": "normal", "lane": 1}, {"id": 387, "time": 130.9583, "type": "normal", "lane": 3}, {"id": 388, "time": 131.1961, "type": "normal", "lane": 0}, {"id": 389, "time": 131.4863, "type": "normal", "lane": 0}, {"id": 390, "time": 131.7141, "type": "normal", "lane": 1}, {"id": 391, "time": 132.2522, "type": "normal", "lane": 1}, {"id": 392, "time": 132.4263, "type": "normal", "lane": 0}, {"id": 393, "time": 132.8283, "type": "normal", "lane": 0}, {"id": 394, "time": 133.008, "type": "normal", "lane": 1}, {"id": 395, "time": 133.2983, "type": "normal", "lane": 2}, {"id": 396, "time": 133.5361, "type": "normal", "lane": 1}, {"id": 397, "time": 133.8844, "type": "normal", "lane": 0}, {"id": 398, "time": 134.2383, "type": "normal", "lane": 1}, {"id": 399, "time": 134.8272, "type": "normal", "lane": 0}, {"id": 400, "time": 135.0041, "type": "normal", "lane": 0}, {"id": 401, "time": 135.2944, "type": "strong", "lane": 1}, {"id": 402, "time": 135.6483, "type": "normal", "lane": 3}, {"id": 403, "time": 135.8861, "type": "normal", "lane": 1}, {"id": 404, "time": 136.1763, "type": "normal", "lane": 0}, {"id": 405, "time": 136.5783, "type": "normal", "lane": 1}, {"id": 406, "time": 136.9422, "type": "normal", "lane": 1}, {"id": 407, "time": 137.4802, "type": "normal", "lane": 0}, {"id": 408, "time": 137.8822, "type": "normal", "lane": 0}, {"id": 409, "time": 138.0563, "type": "normal", "lane": 1}, {"id": 410, "time": 138.2941, "type": "normal", "lane": 0}, {"id": 411, "time": 138.5263, "type": "normal", "lane": 1}, {"id": 412, "time": 138.8802, "type": "normal", "lane": 1}, {"id": 413, "time": 139.118, "type": "normal", "lane": 0}, {"id": 414, "time": 139.4083, "type": "normal", "lane": 1}, {"id": 415, "time": 139.9972, "type": "strong", "lane": 1}, {"id": 416, "time": 140.3383, "type": "normal", "lane": 0}, {"id": 417, "time": 140.6341, "type": "normal", "lane": 0}, {"id": 418, "time": 140.8663, "type": "normal", "lane": 1}, {"id": 419, "time": 141.1522, "type": "normal", "lane": 1}, {"id": 420, "time": 141.3872, "type": "strong", "lane": 2}, {"id": 421, "time": 141.7383, "type": "normal", "lane": 0}, {"id": 422, "time": 141.9861, "type": "normal", "lane": 1}, {"id": 423, "time": 142.2183, "type": "normal", "lane": 0}, {"id": 424, "time": 142.6202, "type": "normal", "lane": 1}, {"id": 425, "time": 142.7944, "type": "normal", "lane": 0}, {"id": 426, "time": 143.1102, "type": "normal", "lane": 1}, {"id": 427, "time": 143.3961, "type": "normal", "lane": 0}, {"id": 428, "time": 143.8561, "type": "normal", "lane": 0}, {"id": 429, "time": 144.3941, "type": "normal", "lane": 1}, {"id": 430, "time": 144.6844, "type": "normal", "lane": 0}, {"id": 431, "time": 144.9322, "type": "normal", "lane": 1}, {"id": 432, "time": 145.2661, "type": "normal", "lane": 1}, {"id": 433, "time": 145.5563, "type": "normal", "lane": 0}, {"id": 434, "time": 145.8622, "type": "normal", "lane": 1}, {"id": 435, "time": 146.5444, "type": "normal", "lane": 0}, {"id": 436, "time": 146.9663, "type": "normal", "lane": 2}, {"id": 437, "time": 147.1461, "type": "normal", "lane": 0}, {"id": 438, "time": 147.3783, "type": "normal", "lane": 1}, {"id": 439, "time": 147.6061, "type": "normal", "lane": 0}, {"id": 440, "time": 148.0761, "type": "normal", "lane": 1}, {"id": 441, "time": 148.3663, "type": "normal", "lane": 1}, {"id": 442, "time": 148.6522, "type": "normal", "lane": 0}, {"id": 443, "time": 149.0061, "type": "normal", "lane": 0}, {"id": 444, "time": 149.3544, "type": "strong", "lane": 2}, {"id": 445, "time": 149.7663, "type": "normal", "lane": 1}, {"id": 446, "time": 150.0622, "type": "normal", "lane": 1}, {"id": 447, "time": 150.4161, "type": "normal", "lane": 0}, {"id": 448, "time": 150.828, "type": "normal", "lane": 0}, {"id": 449, "time": 151.3561, "type": "normal", "lane": 1}, {"id": 450, "time": 151.4722, "type": "normal", "lane": 0}, {"id": 451, "time": 151.7072, "type": "strong", "lane": 1}, {"id": 452, "time": 152.1163, "type": "normal", "lane": 1}, {"id": 453, "time": 152.5963, "type": "normal", "lane": 1}, {"id": 454, "time": 152.8241, "type": "normal", "lane": 0}, {"id": 455, "time": 153.0563, "type": "normal", "lane": 0}, {"id": 456, "time": 153.2841, "type": "normal", "lane": 1}, {"id": 457, "time": 153.5822, "type": "strong", "lane": 1}, {"id": 458, "time": 153.9383, "type": "normal", "lane": 0}, {"id": 459, "time": 154.3983, "type": "normal", "lane": 1}, {"id": 460, "time": 154.8102, "type": "normal", "lane": 0}, {"id": 461, "time": 154.9872, "type": "strong", "lane": 1}, {"id": 462, "time": 155.3963, "type": "normal", "lane": 1}, {"id": 463, "time": 155.6341, "type": "normal", "lane": 1}, {"id": 464, "time": 155.9233, "type": "strong", "lane": 2}, {"id": 465, "time": 156.1522, "type": "normal", "lane": 0}, {"id": 466, "time": 156.448, "type": "normal", "lane": 1}, {"id": 467, "time": 156.7383, "type": "normal", "lane": 0}, {"id": 468, "time": 157.2083, "type": "normal", "lane": 0}, {"id": 469, "time": 157.5622, "type": "normal", "lane": 1}, {"id": 470, "time": 157.7972, "type": "strong", "lane": 2}, {"id": 471, "time": 158.2672, "type": "strong", "lane": 1}, {"id": 472, "time": 158.6183, "type": "normal", "lane": 1}, {"id": 473, "time": 159.0783, "type": "normal", "lane": 0}, {"id": 474, "time": 159.3741, "type": "normal", "lane": 0}, {"id": 475, "time": 159.6063, "type": "normal", "lane": 1}, {"id": 476, "time": 159.8441, "type": "normal", "lane": 0}, {"id": 477, "time": 160.1372, "type": "strong", "lane": 1}, {"id": 478, "time": 160.4302, "type": "normal", "lane": 1}, {"id": 479, "time": 160.9002, "type": "normal", "lane": 0}, {"id": 480, "time": 161.2541, "type": "normal", "lane": 1}, {"id": 481, "time": 161.5444, "type": "strong", "lane": 1}, {"id": 482, "time": 161.8983, "type": "normal", "lane": 0}, {"id": 483, "time": 162.2522, "type": "normal", "lane": 1}, {"id": 484, "time": 162.4263, "type": "normal", "lane": 1}, {"id": 485, "time": 162.7802, "type": "normal", "lane": 0}, {"id": 486, "time": 162.9544, "type": "strong", "lane": 2}, {"id": 487, "time": 163.2402, "type": "normal", "lane": 1}, {"id": 488, "time": 163.4172, "type": "strong", "lane": 2}, {"id": 489, "time": 163.7102, "type": "normal", "lane": 0}, {"id": 490, "time": 163.948, "type": "normal", "lane": 1}, {"id": 491, "time": 164.1802, "type": "normal", "lane": 0}, {"id": 492, "time": 164.3572, "type": "strong", "lane": 2}, {"id": 493, "time": 165.1202, "type": "normal", "lane": 1}, {"id": 494, "time": 165.2972, "type": "strong", "lane": 2}, {"id": 495, "time": 165.6483, "type": "normal", "lane": 0}, {"id": 496, "time": 166.0602, "type": "normal", "lane": 0}, {"id": 497, "time": 166.2344, "type": "strong", "lane": 1}, {"id": 498, "time": 166.5883, "type": "normal", "lane": 1}, {"id": 499, "time": 167.0002, "type": "normal", "lane": 1}, {"id": 500, "time": 167.1722, "type": "strong", "lane": 2}, {"id": 501, "time": 167.5183, "type": "normal", "lane": 0}, {"id": 502, "time": 167.9883, "type": "normal", "lane": 1}, {"id": 503, "time": 168.4002, "type": "normal", "lane": 0}, {"id": 504, "time": 168.5772, "type": "strong", "lane": 2}, {"id": 505, "time": 168.8702, "type": "normal", "lane": 1}, {"id": 506, "time": 169.0472, "type": "strong", "lane": 2}, {"id": 507, "time": 169.3983, "type": "normal", "lane": 0}, {"id": 508, "time": 169.8102, "type": "normal", "lane": 1}, {"id": 509, "time": 169.9822, "type": "strong", "lane": 1}, {"id": 510, "time": 170.3283, "type": "normal", "lane": 0}, {"id": 511, "time": 170.5661, "type": "normal", "lane": 1}, {"id": 512, "time": 170.7983, "type": "normal", "lane": 0}, {"id": 513, "time": 171.0361, "type": "normal", "lane": 1}, {"id": 514, "time": 171.2102, "type": "normal", "lane": 0}, {"id": 515, "time": 171.6222, "type": "normal", "lane": 1}, {"id": 516, "time": 171.7963, "type": "normal", "lane": 0}, {"id": 517, "time": 172.1502, "type": "normal", "lane": 0}, {"id": 518, "time": 172.4461, "type": "normal", "lane": 1}, {"id": 519, "time": 172.6783, "type": "normal", "lane": 0}, {"id": 520, "time": 173.0802, "type": "normal", "lane": 1}, {"id": 521, "time": 173.3861, "type": "normal", "lane": 1}, {"id": 522, "time": 173.6763, "type": "normal", "lane": 0}, {"id": 523, "time": 174.0202, "type": "normal", "lane": 1}, {"id": 524, "time": 174.258, "type": "normal", "lane": 0}, {"id": 525, "time": 174.6644, "type": "strong", "lane": 1}, {"id": 526, "time": 174.9602, "type": "normal", "lane": 1}, {"id": 527, "time": 175.3141, "type": "normal", "lane": 0}, {"id": 528, "time": 175.6086, "type": "strong", "lane": 2}, {"id": 529, "time": 175.9583, "type": "normal", "lane": 3}, {"id": 530, "time": 176.3702, "type": "normal", "lane": 1}, {"id": 531, "time": 176.5422, "type": "strong", "lane": 1}, {"id": 532, "time": 176.8883, "type": "normal", "lane": 0}, {"id": 533, "time": 177.3102, "type": "normal", "lane": 1}, {"id": 534, "time": 177.4263, "type": "normal", "lane": 0}, {"id": 535, "time": 177.7702, "type": "normal", "lane": 1}, {"id": 536, "time": 178.008, "type": "normal", "lane": 0}, {"id": 537, "time": 178.2983, "type": "normal", "lane": 1}, {"id": 538, "time": 178.478, "type": "normal", "lane": 0}, {"id": 539, "time": 179.0061, "type": "normal", "lane": 1}, {"id": 540, "time": 179.2383, "type": "normal", "lane": 0}, {"id": 541, "time": 179.6502, "type": "normal", "lane": 1}, {"id": 542, "time": 179.8272, "type": "strong", "lane": 2}, {"id": 543, "time": 180.1202, "type": "normal", "lane": 0}, {"id": 544, "time": 180.2922, "type": "strong", "lane": 2}, {"id": 545, "time": 180.6383, "type": "normal", "lane": 1}, {"id": 546, "time": 181.1183, "type": "normal", "lane": 0}, {"id": 547, "time": 181.5202, "type": "normal", "lane": 2}, {"id": 548, "time": 181.8261, "type": "normal", "lane": 1}, {"id": 549, "time": 182.248, "type": "normal", "lane": 0}, {"id": 550, "time": 182.6544, "type": "strong", "lane": 2}, {"id": 551, "time": 182.9402, "type": "normal", "lane": 3}, {"id": 552, "time": 183.1144, "type": "strong", "lane": 2}, {"id": 553, "time": 183.4102, "type": "normal", "lane": 0}, {"id": 554, "time": 183.8322, "type": "normal", "lane": 1}, {"id": 555, "time": 184.2241, "type": "normal", "lane": 0}, {"id": 556, "time": 184.598, "type": "normal", "lane": 1}, {"id": 557, "time": 185.2802, "type": "normal", "lane": 0}, {"id": 558, "time": 185.5941, "type": "normal", "lane": 1}, {"id": 559, "time": 185.928, "type": "normal", "lane": 0}, {"id": 560, "time": 186.5622, "type": "normal", "lane": 1}, {"id": 561, "time": 187.0022, "type": "normal", "lane": 0}]}